{
    "dailStartDate": "2002-06-06",
    "dailEndDate": "2007-04-30",
    "dail": 29,
    "parties": [
        {
            "value": "Ceann_Comhairle",
            "label": "Ceann Comhairle"
        },
        {
            "value": "Fianna_Fáil",
            "label": "Fianna Fáil"
        },
        {
            "value": "Fine_Gael",
            "label": "Fine Gael"
        },
        {
            "value": "Green_Party",
            "label": "Green Party"
        },
        {
            "value": "Independent",
            "label": "Independent"
        },
        {
            "value": "Labour_Party",
            "label": "Labour Party"
        },
        {
            "value": "Progressive_Democrats",
            "label": "Progressive Democrats"
        },
        {
            "value": "Sinn_Féin",
            "label": "Sinn Féin"
        },
        {
            "value": "Socialist_Party",
            "label": "Socialist Party"
        }
    ],
    "constituencies": [
        "Carlow-Kilkenny",
        "Cavan-Monaghan",
        "Clare",
        "Cork East",
        "Cork North-Central",
        "Cork North-West",
        "Cork South-Central",
        "Cork South-West",
        "Donegal North-East",
        "Donegal South-West",
        "Dublin Central",
        "Dublin Mid-West",
        "Dublin North",
        "Dublin North-Central",
        "Dublin North-East",
        "Dublin North-West",
        "Dublin South",
        "Dublin South-Central",
        "Dublin South-East",
        "Dublin South-West",
        "Dublin West",
        "Dún Laoghaire",
        "Galway East",
        "Galway West",
        "Kerry North",
        "Kerry South",
        "Kildare North",
        "Kildare South",
        "Laois-Offaly",
        "Limerick East",
        "Limerick West",
        "Longford-Roscommon",
        "Louth",
        "Mayo",
        "Meath",
        "Sligo-Leitrim",
        "Tipperary North",
        "Tipperary South",
        "Waterford",
        "Westmeath",
        "Wexford",
        "Wicklow"
    ],
    "partyAverages": {
        "Fianna Fáil": 72.62,
        "Fine Gael": 58.36,
        "Green Party": 66.82,
        "Independent": 54.65,
        "Labour Party": 75.62,
        "Progressive Democrats": 75.39,
        "Sinn Féin": 72.03,
        "Socialist Party": 68.72
    },
    "partyMedian": {
        "Fianna Fáil": 77.93,
        "Fine Gael": 62.29,
        "Green Party": 69.09,
        "Independent": 58.29,
        "Labour Party": 77.47,
        "Progressive Democrats": 79.88,
        "Sinn Féin": 73.18,
        "Socialist Party": 68.72
    },
    "totalVotes": 537,
    "dateCreated": "25/02/2020 18:01:29"
}