[
    {
        "percentVotes": 39.31,
        "percent_days": 31.43,
        "lastName": "Ahern",
        "votes": 239,
        "total_days": null,
        "total_votes": null,
        "constituency": "Dublin Central",
        "member_id": "Bertie-Ahern.D.1977-07-05",
        "fullName": "Bertie Ahern",
        "firstName": "Bertie",
        "party": "Fianna Fáil",
        "office": false
    },
    {
        "percentVotes": 79.61,
        "percent_days": 77.14,
        "lastName": "Ahern",
        "votes": 484,
        "total_days": null,
        "total_votes": null,
        "constituency": "Louth",
        "member_id": "Dermot-Ahern.D.1987-03-10",
        "fullName": "Dermot Ahern",
        "firstName": "Dermot",
        "party": "Fianna Fáil",
        "office": false
    },
    {
        "percentVotes": 93.42,
        "percent_days": 88.57,
        "lastName": "Ahern",
        "votes": 568,
        "total_days": null,
        "total_votes": null,
        "constituency": "Cork East",
        "member_id": "Michael-Ahern.D.1982-03-09",
        "fullName": "Michael Ahern",
        "firstName": "Michael",
        "party": "Fianna Fáil",
        "office": false
    },
    {
        "percentVotes": 94.57,
        "percent_days": 97.14,
        "lastName": "Ahern",
        "votes": 575,
        "total_days": null,
        "total_votes": null,
        "constituency": "Dublin North-West",
        "member_id": "Noel-Ahern.D.1992-12-14",
        "fullName": "Noel Ahern",
        "firstName": "Noel",
        "party": "Fianna Fáil",
        "office": false
    },
    {
        "percentVotes": 66.78,
        "percent_days": 37.14,
        "lastName": "Allen",
        "votes": 406,
        "total_days": null,
        "total_votes": null,
        "constituency": "Cork North-Central",
        "member_id": "Bernard-Allen.D.1981-06-30",
        "fullName": "Bernard Allen",
        "firstName": "Bernard",
        "party": "Fine Gael",
        "office": false
    },
    {
        "percentVotes": 89.97,
        "percent_days": 90.0,
        "lastName": "Andrews",
        "votes": 547,
        "total_days": null,
        "total_votes": null,
        "constituency": "Dún Laoghaire",
        "member_id": "Barry-Andrews.D.2002-06-06",
        "fullName": "Barry Andrews",
        "firstName": "Barry",
        "party": "Fianna Fáil",
        "office": false
    },
    {
        "percentVotes": 94.24,
        "percent_days": 91.43,
        "lastName": "Andrews",
        "votes": 573,
        "total_days": null,
        "total_votes": null,
        "constituency": "Dublin South-East",
        "member_id": "Chris-Andrews.D.2007-06-14",
        "fullName": "Chris Andrews",
        "firstName": "Chris",
        "party": "Fianna Fáil",
        "office": false
    },
    {
        "percentVotes": 81.09,
        "percent_days": 75.71,
        "lastName": "Ardagh",
        "votes": 493,
        "total_days": null,
        "total_votes": null,
        "constituency": "Dublin South-Central",
        "member_id": "Seán-Ardagh.D.1997-06-26",
        "fullName": "Seán Ardagh",
        "firstName": "Seán",
        "party": "Fianna Fáil",
        "office": false
    },
    {
        "percentVotes": 97.37,
        "percent_days": 95.71,
        "lastName": "Aylward",
        "votes": 592,
        "total_days": null,
        "total_votes": null,
        "constituency": "Carlow-Kilkenny",
        "member_id": "Bobby-Aylward.D.2007-06-14",
        "fullName": "Bobby Aylward",
        "firstName": "Bobby",
        "party": "Fianna Fáil",
        "office": false
    },
    {
        "percentVotes": 81.91,
        "percent_days": 68.57,
        "lastName": "Bannon",
        "votes": 498,
        "total_days": null,
        "total_votes": null,
        "constituency": "Longford-Westmeath",
        "member_id": "James-Bannon.S.2002-09-12",
        "fullName": "James Bannon",
        "firstName": "James",
        "party": "Fine Gael",
        "office": false
    },
    {
        "percentVotes": 81.91,
        "percent_days": 68.57,
        "lastName": "Barrett",
        "votes": 498,
        "total_days": null,
        "total_votes": null,
        "constituency": "Dún Laoghaire",
        "member_id": "Seán-Barrett.D.1981-06-30",
        "fullName": "Seán Barrett",
        "firstName": "Seán",
        "party": "Fine Gael",
        "office": false
    },
    {
        "percentVotes": 83.88,
        "percent_days": 85.71,
        "lastName": "Behan",
        "votes": 510,
        "total_days": null,
        "total_votes": null,
        "constituency": "Wicklow",
        "member_id": "Joe-Behan.D.2007-06-14",
        "fullName": "Joe Behan",
        "firstName": "Joe",
        "party": "Independent",
        "office": false
    },
    {
        "percentVotes": 92.11,
        "percent_days": 92.86,
        "lastName": "Blaney",
        "votes": 560,
        "total_days": null,
        "total_votes": null,
        "constituency": "Donegal North-East",
        "member_id": "Niall-Blaney.D.2002-06-06",
        "fullName": "Niall Blaney",
        "firstName": "Niall",
        "party": "Fianna Fáil",
        "office": false
    },
    {
        "percentVotes": 97.2,
        "percent_days": 97.14,
        "lastName": "Brady",
        "votes": 591,
        "total_days": null,
        "total_votes": null,
        "constituency": "Dublin Central",
        "member_id": "Cyprian-Brady.S.2002-09-12",
        "fullName": "Cyprian Brady",
        "firstName": "Cyprian",
        "party": "Fianna Fáil",
        "office": false
    },
    {
        "percentVotes": 95.89,
        "percent_days": 97.14,
        "lastName": "Brady",
        "votes": 583,
        "total_days": null,
        "total_votes": null,
        "constituency": "Meath West",
        "member_id": "Johnny-Brady.D.1997-06-26",
        "fullName": "Johnny Brady",
        "firstName": "Johnny",
        "party": "Fianna Fáil",
        "office": false
    },
    {
        "percentVotes": 94.74,
        "percent_days": 90.0,
        "lastName": "Brady",
        "votes": 576,
        "total_days": null,
        "total_votes": null,
        "constituency": "Kildare North",
        "member_id": "Áine-Brady.D.2007-06-14",
        "fullName": "Áine Brady",
        "firstName": "Áine",
        "party": "Fianna Fáil",
        "office": false
    },
    {
        "percentVotes": 74.18,
        "percent_days": 70.0,
        "lastName": "Breen",
        "votes": 451,
        "total_days": null,
        "total_votes": null,
        "constituency": "Clare",
        "member_id": "Pat-Breen.D.2002-06-06",
        "fullName": "Pat Breen",
        "firstName": "Pat",
        "party": "Fine Gael",
        "office": false
    },
    {
        "percentVotes": 24.6,
        "percent_days": 20.0,
        "lastName": "Brennan",
        "votes": 31,
        "total_days": 15,
        "total_votes": 126,
        "constituency": "Dublin South",
        "member_id": "Seamus-Brennan.S.1977-10-27",
        "fullName": "Seamus Brennan",
        "firstName": "Seamus",
        "party": "Fianna Fáil",
        "office": false
    },
    {
        "percentVotes": 87.83,
        "percent_days": 77.14,
        "lastName": "Broughan",
        "votes": 534,
        "total_days": null,
        "total_votes": null,
        "constituency": "Dublin North-East",
        "member_id": "Thomas-P-Broughan.D.1992-12-14",
        "fullName": "Thomas P. Broughan",
        "firstName": "Thomas P.",
        "party": "Labour Party",
        "office": false
    },
    {
        "percentVotes": 88.65,
        "percent_days": 81.43,
        "lastName": "Browne",
        "votes": 539,
        "total_days": null,
        "total_votes": null,
        "constituency": "Wexford",
        "member_id": "John-Browne.D.1982-12-14",
        "fullName": "John Browne",
        "firstName": "John",
        "party": "Fianna Fáil",
        "office": false
    },
    {
        "percentVotes": 81.91,
        "percent_days": 81.43,
        "lastName": "Bruton",
        "votes": 498,
        "total_days": null,
        "total_votes": null,
        "constituency": "Dublin North-Central",
        "member_id": "Richard-Bruton.S.1981-10-08",
        "fullName": "Richard Bruton",
        "firstName": "Richard",
        "party": "Fine Gael",
        "office": false
    },
    {
        "percentVotes": 90.95,
        "percent_days": 90.0,
        "lastName": "Burke",
        "votes": 553,
        "total_days": null,
        "total_votes": null,
        "constituency": "Galway East",
        "member_id": "Ulick-Burke.S.1981-10-08",
        "fullName": "Ulick Burke",
        "firstName": "Ulick",
        "party": "Fine Gael",
        "office": false
    },
    {
        "percentVotes": 88.65,
        "percent_days": 87.14,
        "lastName": "Burton",
        "votes": 539,
        "total_days": null,
        "total_votes": null,
        "constituency": "Dublin West",
        "member_id": "Joan-Burton.D.1992-12-14",
        "fullName": "Joan Burton",
        "firstName": "Joan",
        "party": "Labour Party",
        "office": false
    },
    {
        "percentVotes": 82.73,
        "percent_days": 82.86,
        "lastName": "Byrne",
        "votes": 503,
        "total_days": null,
        "total_votes": null,
        "constituency": "Dublin South-Central",
        "member_id": "Catherine-Byrne.D.2007-06-14",
        "fullName": "Catherine Byrne",
        "firstName": "Catherine",
        "party": "Fine Gael",
        "office": false
    },
    {
        "percentVotes": 93.91,
        "percent_days": 88.57,
        "lastName": "Byrne",
        "votes": 571,
        "total_days": null,
        "total_votes": null,
        "constituency": "Meath East",
        "member_id": "Thomas-Byrne.D.2007-06-14",
        "fullName": "Thomas Byrne",
        "firstName": "Thomas",
        "party": "Fianna Fáil",
        "office": false
    },
    {
        "percentVotes": 91.94,
        "percent_days": 88.57,
        "lastName": "Calleary",
        "votes": 559,
        "total_days": null,
        "total_votes": null,
        "constituency": "Mayo",
        "member_id": "Dara-Calleary.D.2007-06-14",
        "fullName": "Dara Calleary",
        "firstName": "Dara",
        "party": "Fianna Fáil",
        "office": false
    },
    {
        "percentVotes": 84.7,
        "percent_days": 82.86,
        "lastName": "Carey",
        "votes": 515,
        "total_days": null,
        "total_votes": null,
        "constituency": "Clare",
        "member_id": "Joe-Carey.D.2007-06-14",
        "fullName": "Joe Carey",
        "firstName": "Joe",
        "party": "Fine Gael",
        "office": false
    },
    {
        "percentVotes": 98.68,
        "percent_days": 100.0,
        "lastName": "Carey",
        "votes": 600,
        "total_days": null,
        "total_votes": null,
        "constituency": "Dublin North-West",
        "member_id": "Pat-Carey.D.1997-06-26",
        "fullName": "Pat Carey",
        "firstName": "Pat",
        "party": "Fianna Fáil",
        "office": false
    },
    {
        "percentVotes": 86.02,
        "percent_days": 72.86,
        "lastName": "Clune",
        "votes": 523,
        "total_days": null,
        "total_votes": null,
        "constituency": "Cork South-Central",
        "member_id": "Deirdre-Clune.D.1997-06-26",
        "fullName": "Deirdre Clune",
        "firstName": "Deirdre",
        "party": "Fine Gael",
        "office": false
    },
    {
        "percentVotes": 90.3,
        "percent_days": 77.14,
        "lastName": "Collins",
        "votes": 549,
        "total_days": null,
        "total_votes": null,
        "constituency": "Limerick West",
        "member_id": "Niall-Collins.D.2007-06-14",
        "fullName": "Niall Collins",
        "firstName": "Niall",
        "party": "Fianna Fáil",
        "office": false
    },
    {
        "percentVotes": 94.24,
        "percent_days": 98.57,
        "lastName": "Conlon",
        "votes": 573,
        "total_days": null,
        "total_votes": null,
        "constituency": "Cavan-Monaghan",
        "member_id": "Margaret-Conlon.D.2007-06-14",
        "fullName": "Margaret Conlon",
        "firstName": "Margaret",
        "party": "Fianna Fáil",
        "office": false
    },
    {
        "percentVotes": 85.69,
        "percent_days": 80.0,
        "lastName": "Connaughton",
        "votes": 521,
        "total_days": null,
        "total_votes": null,
        "constituency": "Galway East",
        "member_id": "Paul-Connaughton.S.1977-10-27",
        "fullName": "Paul Connaughton",
        "firstName": "Paul",
        "party": "Fine Gael",
        "office": false
    },
    {
        "percentVotes": 95.23,
        "percent_days": 95.71,
        "lastName": "Connick",
        "votes": 579,
        "total_days": null,
        "total_votes": null,
        "constituency": "Wexford",
        "member_id": "Seán-Connick.D.2007-06-14",
        "fullName": "Seán Connick",
        "firstName": "Seán",
        "party": "Fianna Fáil",
        "office": false
    },
    {
        "percentVotes": 81.25,
        "percent_days": 80.0,
        "lastName": "Coonan",
        "votes": 494,
        "total_days": null,
        "total_votes": null,
        "constituency": "Tipperary North",
        "member_id": "Noel-Coonan.S.2002-09-12",
        "fullName": "Noel Coonan",
        "firstName": "Noel",
        "party": "Fine Gael",
        "office": false
    },
    {
        "percentVotes": 82.73,
        "percent_days": 80.0,
        "lastName": "Costello",
        "votes": 503,
        "total_days": null,
        "total_votes": null,
        "constituency": "Dublin Central",
        "member_id": "Joe-Costello.S.1989-10-01",
        "fullName": "Joe Costello",
        "firstName": "Joe",
        "party": "Labour Party",
        "office": false
    },
    {
        "percentVotes": 82.4,
        "percent_days": 87.14,
        "lastName": "Coughlan",
        "votes": 501,
        "total_days": null,
        "total_votes": null,
        "constituency": "Donegal South-West",
        "member_id": "Mary-Coughlan.D.1987-03-10",
        "fullName": "Mary Coughlan",
        "firstName": "Mary",
        "party": "Fianna Fáil",
        "office": false
    },
    {
        "percentVotes": 81.91,
        "percent_days": 72.86,
        "lastName": "Coveney",
        "votes": 498,
        "total_days": null,
        "total_votes": null,
        "constituency": "Cork South-Central",
        "member_id": "Simon-Coveney.D.1998-10-23",
        "fullName": "Simon Coveney",
        "firstName": "Simon",
        "party": "Fine Gael",
        "office": false
    },
    {
        "percentVotes": 48.52,
        "percent_days": 30.0,
        "lastName": "Cowen",
        "votes": 295,
        "total_days": null,
        "total_votes": null,
        "constituency": "Laois-Offaly",
        "member_id": "Brian-Cowen.D.1984-06-14",
        "fullName": "Brian Cowen",
        "firstName": "Brian",
        "party": "Fianna Fáil",
        "office": false
    },
    {
        "percentVotes": 85.69,
        "percent_days": 80.0,
        "lastName": "Crawford",
        "votes": 521,
        "total_days": null,
        "total_votes": null,
        "constituency": "Cavan-Monaghan",
        "member_id": "Seymour-Crawford.D.1992-12-14",
        "fullName": "Seymour Crawford",
        "firstName": "Seymour",
        "party": "Fine Gael",
        "office": false
    },
    {
        "percentVotes": 80.1,
        "percent_days": 70.0,
        "lastName": "Creed",
        "votes": 487,
        "total_days": null,
        "total_votes": null,
        "constituency": "Cork North-West",
        "member_id": "Michael-Creed.D.1989-06-29",
        "fullName": "Michael Creed",
        "firstName": "Michael",
        "party": "Fine Gael",
        "office": false
    },
    {
        "percentVotes": 95.07,
        "percent_days": 94.29,
        "lastName": "Cregan",
        "votes": 578,
        "total_days": null,
        "total_votes": null,
        "constituency": "Limerick West",
        "member_id": "John-Cregan.S.1998-06-23",
        "fullName": "John Cregan",
        "firstName": "John",
        "party": "Fianna Fáil",
        "office": false
    },
    {
        "percentVotes": 77.14,
        "percent_days": 75.71,
        "lastName": "Creighton",
        "votes": 469,
        "total_days": null,
        "total_votes": null,
        "constituency": "Dublin South-East",
        "member_id": "Lucinda-Creighton.D.2007-06-14",
        "fullName": "Lucinda Creighton",
        "firstName": "Lucinda",
        "party": "Fine Gael",
        "office": false
    },
    {
        "percentVotes": 90.46,
        "percent_days": 91.43,
        "lastName": "Cuffe",
        "votes": 550,
        "total_days": null,
        "total_votes": null,
        "constituency": "Dún Laoghaire",
        "member_id": "Ciarán-Cuffe.D.2002-06-06",
        "fullName": "Ciarán Cuffe",
        "firstName": "Ciarán",
        "party": "Green Party",
        "office": false
    },
    {
        "percentVotes": 56.09,
        "percent_days": 50.0,
        "lastName": "Cullen",
        "votes": 341,
        "total_days": null,
        "total_votes": null,
        "constituency": "Waterford",
        "member_id": "Martin-Cullen.D.1987-03-10",
        "fullName": "Martin Cullen",
        "firstName": "Martin",
        "party": "Fianna Fáil",
        "office": false
    },
    {
        "percentVotes": 95.23,
        "percent_days": 90.0,
        "lastName": "Curran",
        "votes": 579,
        "total_days": null,
        "total_votes": null,
        "constituency": "Dublin Mid-West",
        "member_id": "John-Curran.D.2002-06-06",
        "fullName": "John Curran",
        "firstName": "John",
        "party": "Fianna Fáil",
        "office": false
    },
    {
        "percentVotes": 82.89,
        "percent_days": 78.57,
        "lastName": "D'Arcy",
        "votes": 504,
        "total_days": null,
        "total_votes": null,
        "constituency": "Wexford",
        "member_id": "Michael-D'Arcy.D.2007-06-14",
        "fullName": "Michael D'Arcy",
        "firstName": "Michael",
        "party": "Fine Gael",
        "office": false
    },
    {
        "percentVotes": 71.71,
        "percent_days": 61.43,
        "lastName": "Deasy",
        "votes": 436,
        "total_days": null,
        "total_votes": null,
        "constituency": "Waterford",
        "member_id": "John-Deasy.D.2002-06-06",
        "fullName": "John Deasy",
        "firstName": "John",
        "party": "Fine Gael",
        "office": false
    },
    {
        "percentVotes": 90.13,
        "percent_days": 87.14,
        "lastName": "Deenihan",
        "votes": 548,
        "total_days": null,
        "total_votes": null,
        "constituency": "Kerry North",
        "member_id": "Jimmy-Deenihan.S.1983-02-23",
        "fullName": "Jimmy Deenihan",
        "firstName": "Jimmy",
        "party": "Fine Gael",
        "office": false
    },
    {
        "percentVotes": 84.7,
        "percent_days": 82.86,
        "lastName": "Dempsey",
        "votes": 515,
        "total_days": null,
        "total_votes": null,
        "constituency": "Meath West",
        "member_id": "Noel-Dempsey.D.1987-03-10",
        "fullName": "Noel Dempsey",
        "firstName": "Noel",
        "party": "Fianna Fáil",
        "office": false
    },
    {
        "percentVotes": 91.12,
        "percent_days": 87.14,
        "lastName": "Devins",
        "votes": 554,
        "total_days": null,
        "total_votes": null,
        "constituency": "Sligo-North Leitrim",
        "member_id": "Jimmy-Devins.D.2002-06-06",
        "fullName": "Jimmy Devins",
        "firstName": "Jimmy",
        "party": "Fianna Fáil",
        "office": false
    },
    {
        "percentVotes": 94.12,
        "percent_days": 80.0,
        "lastName": "Doherty",
        "votes": 48,
        "total_days": 5,
        "total_votes": 51,
        "constituency": "Donegal South-West",
        "member_id": "Pearse-Doherty.S.2007-07-23",
        "fullName": "Pearse Doherty",
        "firstName": "Pearse",
        "party": "Sinn Féin",
        "office": false
    },
    {
        "percentVotes": 95.23,
        "percent_days": 91.43,
        "lastName": "Dooley",
        "votes": 579,
        "total_days": null,
        "total_votes": null,
        "constituency": "Clare",
        "member_id": "Timmy-Dooley.S.2002-09-12",
        "fullName": "Timmy Dooley",
        "firstName": "Timmy",
        "party": "Fianna Fáil",
        "office": false
    },
    {
        "percentVotes": 87.83,
        "percent_days": 85.71,
        "lastName": "Doyle",
        "votes": 534,
        "total_days": null,
        "total_votes": null,
        "constituency": "Wicklow",
        "member_id": "Andrew-Doyle.D.2007-06-14",
        "fullName": "Andrew Doyle",
        "firstName": "Andrew",
        "party": "Fine Gael",
        "office": false
    },
    {
        "percentVotes": 89.31,
        "percent_days": 92.86,
        "lastName": "Durkan",
        "votes": 543,
        "total_days": null,
        "total_votes": null,
        "constituency": "Kildare North",
        "member_id": "Bernard-Durkan.D.1981-06-30",
        "fullName": "Bernard Durkan",
        "firstName": "Bernard",
        "party": "Fine Gael",
        "office": false
    },
    {
        "percentVotes": 83.22,
        "percent_days": 80.0,
        "lastName": "English",
        "votes": 506,
        "total_days": null,
        "total_votes": null,
        "constituency": "Meath West",
        "member_id": "Damien-English.D.2002-06-06",
        "fullName": "Damien English",
        "firstName": "Damien",
        "party": "Fine Gael",
        "office": false
    },
    {
        "percentVotes": 72.37,
        "percent_days": 70.0,
        "lastName": "Enright",
        "votes": 440,
        "total_days": null,
        "total_votes": null,
        "constituency": "Laois-Offaly",
        "member_id": "Olwyn-Enright.D.2002-06-06",
        "fullName": "Olwyn Enright",
        "firstName": "Olwyn",
        "party": "Fine Gael",
        "office": false
    },
    {
        "percentVotes": 71.88,
        "percent_days": 65.71,
        "lastName": "Fahey",
        "votes": 437,
        "total_days": null,
        "total_votes": null,
        "constituency": "Galway West",
        "member_id": "Frank-Fahey.D.1982-03-09",
        "fullName": "Frank Fahey",
        "firstName": "Frank",
        "party": "Fianna Fáil",
        "office": false
    },
    {
        "percentVotes": 88.98,
        "percent_days": 90.0,
        "lastName": "Feighan",
        "votes": 541,
        "total_days": null,
        "total_votes": null,
        "constituency": "Roscommon-South-Leitrim",
        "member_id": "Frank-Feighan.S.2002-09-12",
        "fullName": "Frankie Feighan",
        "firstName": "Frankie",
        "party": "Fine Gael",
        "office": false
    },
    {
        "percentVotes": 75.0,
        "percent_days": 68.57,
        "lastName": "Ferris",
        "votes": 456,
        "total_days": null,
        "total_votes": null,
        "constituency": "Kerry North",
        "member_id": "Martin-Ferris.D.2002-06-06",
        "fullName": "Martin Ferris",
        "firstName": "Martin",
        "party": "Sinn Féin",
        "office": false
    },
    {
        "percentVotes": 85.86,
        "percent_days": 82.86,
        "lastName": "Finneran",
        "votes": 522,
        "total_days": null,
        "total_votes": null,
        "constituency": "Roscommon-South-Leitrim",
        "member_id": "Michael-Finneran.S.1989-10-01",
        "fullName": "Michael Finneran",
        "firstName": "Michael",
        "party": "Fianna Fáil",
        "office": false
    },
    {
        "percentVotes": 98.19,
        "percent_days": 97.14,
        "lastName": "Fitzpatrick",
        "votes": 597,
        "total_days": null,
        "total_votes": null,
        "constituency": "Kildare North",
        "member_id": "Michael-Fitzpatrick.D.2007-06-14",
        "fullName": "Michael Fitzpatrick",
        "firstName": "Michael",
        "party": "Fianna Fáil",
        "office": false
    },
    {
        "percentVotes": 84.54,
        "percent_days": 87.14,
        "lastName": "Flanagan",
        "votes": 514,
        "total_days": null,
        "total_votes": null,
        "constituency": "Laois-Offaly",
        "member_id": "Charles-Flanagan.D.1987-03-10",
        "fullName": "Charles Flanagan",
        "firstName": "Charles",
        "party": "Fine Gael",
        "office": false
    },
    {
        "percentVotes": 90.3,
        "percent_days": 87.14,
        "lastName": "Flanagan",
        "votes": 549,
        "total_days": null,
        "total_votes": null,
        "constituency": "Dublin North-East",
        "member_id": "Terence-Flanagan.D.2007-06-14",
        "fullName": "Terence Flanagan",
        "firstName": "Terence",
        "party": "Fine Gael",
        "office": false
    },
    {
        "percentVotes": 87.66,
        "percent_days": 67.14,
        "lastName": "Fleming",
        "votes": 533,
        "total_days": null,
        "total_votes": null,
        "constituency": "Laois-Offaly",
        "member_id": "Seán-Fleming.D.1997-06-26",
        "fullName": "Sean Fleming",
        "firstName": "Sean",
        "party": "Fianna Fáil",
        "office": false
    },
    {
        "percentVotes": 89.31,
        "percent_days": 88.57,
        "lastName": "Flynn",
        "votes": 543,
        "total_days": null,
        "total_votes": null,
        "constituency": "Mayo",
        "member_id": "Beverley-Flynn.D.1997-06-26",
        "fullName": "Beverley Flynn",
        "firstName": "Beverley",
        "party": "Independent",
        "office": false
    },
    {
        "percentVotes": 37.99,
        "percent_days": 32.81,
        "lastName": "Gallagher",
        "votes": 212,
        "total_days": 64,
        "total_votes": 558,
        "constituency": "Donegal South-West",
        "member_id": "Pat-the-Cope-Gallagher.D.1981-06-30",
        "fullName": "Pat the Cope Gallagher",
        "firstName": "Pat the Cope",
        "party": "Fianna Fáil",
        "office": false
    },
    {
        "percentVotes": 83.55,
        "percent_days": 78.57,
        "lastName": "Gilmore",
        "votes": 508,
        "total_days": null,
        "total_votes": null,
        "constituency": "Dún Laoghaire",
        "member_id": "Eamon-Gilmore.D.1989-06-29",
        "fullName": "Eamon Gilmore",
        "firstName": "Eamon",
        "party": "Labour Party",
        "office": false
    },
    {
        "percentVotes": 94.41,
        "percent_days": 98.57,
        "lastName": "Gogarty",
        "votes": 574,
        "total_days": null,
        "total_votes": null,
        "constituency": "Dublin Mid-West",
        "member_id": "Paul-Nicholas-Gogarty.D.2002-06-06",
        "fullName": "Paul Nicholas Gogarty",
        "firstName": "Paul Nicholas",
        "party": "Green Party",
        "office": false
    },
    {
        "percentVotes": 79.28,
        "percent_days": 77.14,
        "lastName": "Gormley",
        "votes": 482,
        "total_days": null,
        "total_votes": null,
        "constituency": "Dublin South-East",
        "member_id": "John-Gormley.D.1997-06-26",
        "fullName": "John Gormley",
        "firstName": "John",
        "party": "Green Party",
        "office": false
    },
    {
        "percentVotes": 83.22,
        "percent_days": 75.71,
        "lastName": "Grealish",
        "votes": 506,
        "total_days": null,
        "total_votes": null,
        "constituency": "Galway West",
        "member_id": "Noel-Grealish.D.2002-06-06",
        "fullName": "Noel Grealish",
        "firstName": "Noel",
        "party": "Independent",
        "office": false
    },
    {
        "percentVotes": 22.22,
        "percent_days": 17.39,
        "lastName": "Gregory",
        "votes": 46,
        "total_days": 23,
        "total_votes": 207,
        "constituency": "Dublin Central",
        "member_id": "Tony-Gregory.D.1982-03-09",
        "fullName": "Tony Gregory",
        "firstName": "Tony",
        "party": "Independent",
        "office": false
    },
    {
        "percentVotes": 82.73,
        "percent_days": 81.43,
        "lastName": "Hanafin",
        "votes": 503,
        "total_days": null,
        "total_votes": null,
        "constituency": "Dún Laoghaire",
        "member_id": "Mary-Hanafin.D.1997-06-26",
        "fullName": "Mary Hanafin",
        "firstName": "Mary",
        "party": "Fianna Fáil",
        "office": false
    },
    {
        "percentVotes": 78.45,
        "percent_days": 75.71,
        "lastName": "Harney",
        "votes": 477,
        "total_days": null,
        "total_votes": null,
        "constituency": "Dublin Mid-West",
        "member_id": "Mary-Harney.S.1977-10-27",
        "fullName": "Mary Harney",
        "firstName": "Mary",
        "party": "Independent",
        "office": false
    },
    {
        "percentVotes": 93.42,
        "percent_days": 90.0,
        "lastName": "Haughey",
        "votes": 568,
        "total_days": null,
        "total_votes": null,
        "constituency": "Dublin North-Central",
        "member_id": "Seán-Haughey.S.1987-04-25",
        "fullName": "Seán Haughey",
        "firstName": "Seán",
        "party": "Fianna Fáil",
        "office": false
    },
    {
        "percentVotes": 83.22,
        "percent_days": 85.71,
        "lastName": "Hayes",
        "votes": 506,
        "total_days": null,
        "total_votes": null,
        "constituency": "Dublin South-West",
        "member_id": "Brian-Hayes.S.1995-12-20",
        "fullName": "Brian Hayes",
        "firstName": "Brian",
        "party": "Fine Gael",
        "office": false
    },
    {
        "percentVotes": 80.92,
        "percent_days": 68.57,
        "lastName": "Hayes",
        "votes": 492,
        "total_days": null,
        "total_votes": null,
        "constituency": "Tipperary South",
        "member_id": "Tom-Hayes.S.1997-09-17",
        "fullName": "Tom Hayes",
        "firstName": "Tom",
        "party": "Fine Gael",
        "office": false
    },
    {
        "percentVotes": 79.93,
        "percent_days": 71.43,
        "lastName": "Healy-Rae",
        "votes": 486,
        "total_days": null,
        "total_votes": null,
        "constituency": "Kerry South",
        "member_id": "Jackie-Healy-Rae.D.1997-06-26",
        "fullName": "Jackie Healy-Rae",
        "firstName": "Jackie",
        "party": "Independent",
        "office": false
    },
    {
        "percentVotes": 84.87,
        "percent_days": 82.86,
        "lastName": "Higgins",
        "votes": 516,
        "total_days": null,
        "total_votes": null,
        "constituency": "Galway West",
        "member_id": "Michael-D-Higgins.S.1973-06-01",
        "fullName": "Michael D. Higgins",
        "firstName": "Michael D.",
        "party": "Labour Party",
        "office": false
    },
    {
        "percentVotes": 88.82,
        "percent_days": 90.0,
        "lastName": "Hoctor",
        "votes": 540,
        "total_days": null,
        "total_votes": null,
        "constituency": "Tipperary North",
        "member_id": "Máire-Hoctor.D.2002-06-06",
        "fullName": "Máire Hoctor",
        "firstName": "Máire",
        "party": "Fianna Fáil",
        "office": false
    },
    {
        "percentVotes": 80.1,
        "percent_days": 78.57,
        "lastName": "Hogan",
        "votes": 487,
        "total_days": null,
        "total_votes": null,
        "constituency": "Carlow-Kilkenny",
        "member_id": "Phil-Hogan.S.1987-04-25",
        "fullName": "Phil Hogan",
        "firstName": "Phil",
        "party": "Fine Gael",
        "office": false
    },
    {
        "percentVotes": 79.11,
        "percent_days": 78.57,
        "lastName": "Howlin",
        "votes": 481,
        "total_days": null,
        "total_votes": null,
        "constituency": "Wexford",
        "member_id": "Brendan-Howlin.S.1983-02-23",
        "fullName": "Brendan Howlin",
        "firstName": "Brendan",
        "party": "Labour Party",
        "office": false
    },
    {
        "percentVotes": 85.69,
        "percent_days": 85.71,
        "lastName": "Kehoe",
        "votes": 521,
        "total_days": null,
        "total_votes": null,
        "constituency": "Wexford",
        "member_id": "Paul-Kehoe.D.2002-06-06",
        "fullName": "Paul Kehoe",
        "firstName": "Paul",
        "party": "Fine Gael",
        "office": false
    },
    {
        "percentVotes": 83.55,
        "percent_days": 80.0,
        "lastName": "Kelleher",
        "votes": 508,
        "total_days": null,
        "total_votes": null,
        "constituency": "Cork North-Central",
        "member_id": "Billy-Kelleher.S.1993-02-17",
        "fullName": "Billy Kelleher",
        "firstName": "Billy",
        "party": "Fianna Fáil",
        "office": false
    },
    {
        "percentVotes": 92.76,
        "percent_days": 91.43,
        "lastName": "Kelly",
        "votes": 564,
        "total_days": null,
        "total_votes": null,
        "constituency": "Longford-Westmeath",
        "member_id": "Peter-Kelly.D.2002-06-06",
        "fullName": "Peter Kelly",
        "firstName": "Peter",
        "party": "Fianna Fáil",
        "office": false
    },
    {
        "percentVotes": 94.41,
        "percent_days": 84.29,
        "lastName": "Kenneally",
        "votes": 574,
        "total_days": null,
        "total_votes": null,
        "constituency": "Waterford",
        "member_id": "Brendan-Kenneally.D.1989-06-29",
        "fullName": "Brendan Kenneally",
        "firstName": "Brendan",
        "party": "Fianna Fáil",
        "office": false
    },
    {
        "percentVotes": 99.18,
        "percent_days": 98.57,
        "lastName": "Kennedy",
        "votes": 603,
        "total_days": null,
        "total_votes": null,
        "constituency": "Dublin North",
        "member_id": "Michael-Kennedy.D.2007-06-14",
        "fullName": "Michael Kennedy",
        "firstName": "Michael",
        "party": "Fianna Fáil",
        "office": false
    },
    {
        "percentVotes": 66.78,
        "percent_days": 58.57,
        "lastName": "Kenny",
        "votes": 406,
        "total_days": null,
        "total_votes": null,
        "constituency": "Mayo",
        "member_id": "Enda-Kenny.D.1975-11-12",
        "fullName": "Enda Kenny",
        "firstName": "Enda",
        "party": "Fine Gael",
        "office": false
    },
    {
        "percentVotes": 77.14,
        "percent_days": 78.57,
        "lastName": "Killeen",
        "votes": 469,
        "total_days": null,
        "total_votes": null,
        "constituency": "Clare",
        "member_id": "Tony-Killeen.D.1992-12-14",
        "fullName": "Tony Killeen",
        "firstName": "Tony",
        "party": "Fianna Fáil",
        "office": false
    },
    {
        "percentVotes": 55.1,
        "percent_days": 48.57,
        "lastName": "Kirk",
        "votes": 335,
        "total_days": null,
        "total_votes": null,
        "constituency": "Louth",
        "member_id": "Seamus-Kirk.D.1982-12-14",
        "fullName": "Seamus Kirk",
        "firstName": "Seamus",
        "party": "Fianna Fáil",
        "office": false
    },
    {
        "percentVotes": 0,
        "percent_days": 0,
        "lastName": "Kitt",
        "votes": 0,
        "total_days": null,
        "total_votes": null,
        "constituency": "Galway East",
        "member_id": "Michael-P-Kitt.D.1975-03-04",
        "fullName": "Michael P. Kitt",
        "firstName": "Michael P.",
        "party": "Fianna Fáil",
        "office": false
    },
    {
        "percentVotes": 90.95,
        "percent_days": 90.0,
        "lastName": "Kitt",
        "votes": 553,
        "total_days": null,
        "total_votes": null,
        "constituency": "Dublin South",
        "member_id": "Tom-Kitt.D.1987-03-10",
        "fullName": "Tom Kitt",
        "firstName": "Tom",
        "party": "Fianna Fáil",
        "office": false
    },
    {
        "percentVotes": 37.46,
        "percent_days": 25.0,
        "lastName": "Lee",
        "votes": 121,
        "total_days": 36,
        "total_votes": 323,
        "constituency": "Dublin South",
        "member_id": "George-Lee.D.2009-06-05",
        "fullName": "George Lee",
        "firstName": "George",
        "party": "Fine Gael",
        "office": false
    },
    {
        "percentVotes": 76.81,
        "percent_days": 72.86,
        "lastName": "Lenihan",
        "votes": 467,
        "total_days": null,
        "total_votes": null,
        "constituency": "Dublin West",
        "member_id": "Brian-Lenihan.D.1996-04-02",
        "fullName": "Brian Lenihan",
        "firstName": "Brian",
        "party": "Fianna Fáil",
        "office": false
    },
    {
        "percentVotes": 85.03,
        "percent_days": 77.14,
        "lastName": "Lenihan",
        "votes": 517,
        "total_days": null,
        "total_votes": null,
        "constituency": "Dublin South-West",
        "member_id": "Conor-Lenihan.D.1997-06-26",
        "fullName": "Conor Lenihan",
        "firstName": "Conor",
        "party": "Fianna Fáil",
        "office": false
    },
    {
        "percentVotes": 63.49,
        "percent_days": 44.29,
        "lastName": "Lowry",
        "votes": 386,
        "total_days": null,
        "total_votes": null,
        "constituency": "Tipperary North",
        "member_id": "Michael-Lowry.D.1987-03-10",
        "fullName": "Michael Lowry",
        "firstName": "Michael",
        "party": "Independent",
        "office": false
    },
    {
        "percentVotes": 88.32,
        "percent_days": 84.29,
        "lastName": "Lynch",
        "votes": 537,
        "total_days": null,
        "total_votes": null,
        "constituency": "Cork South-Central",
        "member_id": "Ciaran-Lynch.D.2007-06-14",
        "fullName": "Ciaran Lynch",
        "firstName": "Ciaran",
        "party": "Labour Party",
        "office": false
    },
    {
        "percentVotes": 82.57,
        "percent_days": 75.71,
        "lastName": "Lynch",
        "votes": 502,
        "total_days": null,
        "total_votes": null,
        "constituency": "Cork North-Central",
        "member_id": "Kathleen-Lynch.D.1994-11-10",
        "fullName": "Kathleen Lynch",
        "firstName": "Kathleen",
        "party": "Labour Party",
        "office": false
    },
    {
        "percentVotes": 79.77,
        "percent_days": 70.0,
        "lastName": "Mansergh",
        "votes": 485,
        "total_days": null,
        "total_votes": null,
        "constituency": "Tipperary South",
        "member_id": "Dr-Martin-Mansergh.S.2002-09-12",
        "fullName": "Dr Martin Mansergh",
        "firstName": "Dr Martin",
        "party": "Fianna Fáil",
        "office": false
    },
    {
        "percentVotes": 61.35,
        "percent_days": 51.43,
        "lastName": "Martin",
        "votes": 373,
        "total_days": null,
        "total_votes": null,
        "constituency": "Cork South-Central",
        "member_id": "Micheál-Martin.D.1989-06-29",
        "fullName": "Micheál Martin",
        "firstName": "Micheál",
        "party": "Fianna Fáil",
        "office": false
    },
    {
        "percentVotes": 90.46,
        "percent_days": 80.0,
        "lastName": "McCormack",
        "votes": 550,
        "total_days": null,
        "total_votes": null,
        "constituency": "Galway West",
        "member_id": "Pádraic-McCormack.S.1987-04-25",
        "fullName": "Pádraic McCormack",
        "firstName": "Pádraic",
        "party": "Fine Gael",
        "office": false
    },
    {
        "percentVotes": 23.68,
        "percent_days": 5.71,
        "lastName": "McDaid",
        "votes": 144,
        "total_days": null,
        "total_votes": null,
        "constituency": "Donegal North-East",
        "member_id": "James-McDaid.D.1989-06-29",
        "fullName": "James McDaid",
        "firstName": "James",
        "party": "Independent",
        "office": false
    },
    {
        "percentVotes": 94.41,
        "percent_days": 95.71,
        "lastName": "McEllistrim",
        "votes": 574,
        "total_days": null,
        "total_votes": null,
        "constituency": "Kerry North",
        "member_id": "Tom-McEllistrim.D.2002-06-06",
        "fullName": "Tom McEllistrim",
        "firstName": "Tom",
        "party": "Fianna Fáil",
        "office": false
    },
    {
        "percentVotes": 77.96,
        "percent_days": 74.29,
        "lastName": "McEntee",
        "votes": 474,
        "total_days": null,
        "total_votes": null,
        "constituency": "Meath East",
        "member_id": "Shane-McEntee.D.2005-03-11",
        "fullName": "Shane McEntee",
        "firstName": "Shane",
        "party": "Fine Gael",
        "office": false
    },
    {
        "percentVotes": 78.62,
        "percent_days": 81.43,
        "lastName": "McGinley",
        "votes": 478,
        "total_days": null,
        "total_votes": null,
        "constituency": "Donegal South-West",
        "member_id": "Dinny-McGinley.D.1982-03-09",
        "fullName": "Dinny McGinley",
        "firstName": "Dinny",
        "party": "Fine Gael",
        "office": false
    },
    {
        "percentVotes": 87.17,
        "percent_days": 74.29,
        "lastName": "McGrath",
        "votes": 530,
        "total_days": null,
        "total_votes": null,
        "constituency": "Dublin North-Central",
        "member_id": "Finian-McGrath.D.2002-06-06",
        "fullName": "Finian McGrath",
        "firstName": "Finian",
        "party": "Independent",
        "office": false
    },
    {
        "percentVotes": 91.78,
        "percent_days": 88.57,
        "lastName": "McGrath",
        "votes": 558,
        "total_days": null,
        "total_votes": null,
        "constituency": "Tipperary South",
        "member_id": "Mattie-McGrath.D.2007-06-14",
        "fullName": "Mattie McGrath",
        "firstName": "Mattie",
        "party": "Independent",
        "office": false
    },
    {
        "percentVotes": 94.9,
        "percent_days": 80.0,
        "lastName": "McGrath",
        "votes": 577,
        "total_days": null,
        "total_votes": null,
        "constituency": "Cork South-Central",
        "member_id": "Michael-McGrath.D.2007-06-14",
        "fullName": "Michael McGrath",
        "firstName": "Michael",
        "party": "Fianna Fáil",
        "office": false
    },
    {
        "percentVotes": 82.89,
        "percent_days": 68.57,
        "lastName": "McGuinness",
        "votes": 504,
        "total_days": null,
        "total_votes": null,
        "constituency": "Carlow-Kilkenny",
        "member_id": "John-McGuinness.D.1997-06-26",
        "fullName": "John McGuinness",
        "firstName": "John",
        "party": "Fianna Fáil",
        "office": false
    },
    {
        "percentVotes": 78.12,
        "percent_days": 68.57,
        "lastName": "McHugh",
        "votes": 475,
        "total_days": null,
        "total_votes": null,
        "constituency": "Donegal North-East",
        "member_id": "Joe-McHugh.S.2002-09-12",
        "fullName": "Joe McHugh",
        "firstName": "Joe",
        "party": "Fine Gael",
        "office": false
    },
    {
        "percentVotes": 82.89,
        "percent_days": 84.29,
        "lastName": "McManus",
        "votes": 504,
        "total_days": null,
        "total_votes": null,
        "constituency": "Wicklow",
        "member_id": "Liz-McManus.D.1992-12-14",
        "fullName": "Liz McManus",
        "firstName": "Liz",
        "party": "Labour Party",
        "office": false
    },
    {
        "percentVotes": 82.89,
        "percent_days": 67.14,
        "lastName": "Mitchell",
        "votes": 504,
        "total_days": null,
        "total_votes": null,
        "constituency": "Dublin South",
        "member_id": "Olivia-Mitchell.D.1997-06-26",
        "fullName": "Olivia Mitchell",
        "firstName": "Olivia",
        "party": "Fine Gael",
        "office": false
    },
    {
        "percentVotes": 87.66,
        "percent_days": 87.14,
        "lastName": "Moloney",
        "votes": 533,
        "total_days": null,
        "total_votes": null,
        "constituency": "Laois-Offaly",
        "member_id": "John-Moloney.D.1997-06-26",
        "fullName": "John Moloney",
        "firstName": "John",
        "party": "Fianna Fáil",
        "office": false
    },
    {
        "percentVotes": 71.88,
        "percent_days": 67.14,
        "lastName": "Morgan",
        "votes": 437,
        "total_days": null,
        "total_votes": null,
        "constituency": "Louth",
        "member_id": "Arthur-Morgan.D.2002-06-06",
        "fullName": "Arthur Morgan",
        "firstName": "Arthur",
        "party": "Sinn Féin",
        "office": false
    },
    {
        "percentVotes": 92.93,
        "percent_days": 84.29,
        "lastName": "Moynihan",
        "votes": 565,
        "total_days": null,
        "total_votes": null,
        "constituency": "Cork North-West",
        "member_id": "Michael-Moynihan.D.1997-06-26",
        "fullName": "Michael Moynihan",
        "firstName": "Michael",
        "party": "Fianna Fáil",
        "office": false
    },
    {
        "percentVotes": 90.3,
        "percent_days": 82.86,
        "lastName": "Mulcahy",
        "votes": 549,
        "total_days": null,
        "total_votes": null,
        "constituency": "Dublin South-Central",
        "member_id": "Michael-Mulcahy.S.1994-12-13",
        "fullName": "Michael Mulcahy",
        "firstName": "Michael",
        "party": "Fianna Fáil",
        "office": false
    },
    {
        "percentVotes": 79.77,
        "percent_days": 72.86,
        "lastName": "Naughten",
        "votes": 485,
        "total_days": null,
        "total_votes": null,
        "constituency": "Roscommon-South-Leitrim",
        "member_id": "Denis-Naughten.S.1997-01-28",
        "fullName": "Denis Naughten",
        "firstName": "Denis",
        "party": "Fine Gael",
        "office": false
    },
    {
        "percentVotes": 88.16,
        "percent_days": 87.14,
        "lastName": "Neville",
        "votes": 536,
        "total_days": null,
        "total_votes": null,
        "constituency": "Limerick West",
        "member_id": "Dan-Neville.S.1989-10-01",
        "fullName": "Dan Neville",
        "firstName": "Dan",
        "party": "Fine Gael",
        "office": false
    },
    {
        "percentVotes": 94.74,
        "percent_days": 88.57,
        "lastName": "Nolan",
        "votes": 576,
        "total_days": null,
        "total_votes": null,
        "constituency": "Carlow-Kilkenny",
        "member_id": "M-J-Nolan.S.1982-05-13",
        "fullName": "M. J. Nolan",
        "firstName": "M. J.",
        "party": "Fianna Fáil",
        "office": false
    },
    {
        "percentVotes": 68.75,
        "percent_days": 65.71,
        "lastName": "Noonan",
        "votes": 418,
        "total_days": null,
        "total_votes": null,
        "constituency": "Limerick East",
        "member_id": "Michael-Noonan.D.1981-06-30",
        "fullName": "Michael Noonan",
        "firstName": "Michael",
        "party": "Fine Gael",
        "office": false
    },
    {
        "percentVotes": 90.13,
        "percent_days": 77.14,
        "lastName": "O'Brien",
        "votes": 548,
        "total_days": null,
        "total_votes": null,
        "constituency": "Dublin North",
        "member_id": "Darragh-O'Brien.D.2007-06-14",
        "fullName": "Darragh O'Brien",
        "firstName": "Darragh",
        "party": "Fianna Fáil",
        "office": false
    },
    {
        "percentVotes": 97.04,
        "percent_days": 95.71,
        "lastName": "O'Connor",
        "votes": 590,
        "total_days": null,
        "total_votes": null,
        "constituency": "Dublin South-West",
        "member_id": "Charlie-O'Connor.D.2002-06-06",
        "fullName": "Charlie O'Connor",
        "firstName": "Charlie",
        "party": "Fianna Fáil",
        "office": false
    },
    {
        "percentVotes": 85.69,
        "percent_days": 82.86,
        "lastName": "O'Dea",
        "votes": 521,
        "total_days": null,
        "total_votes": null,
        "constituency": "Limerick East",
        "member_id": "Willie-O'Dea.D.1982-03-09",
        "fullName": "Willie O'Dea",
        "firstName": "Willie",
        "party": "Fianna Fáil",
        "office": false
    },
    {
        "percentVotes": 87.17,
        "percent_days": 88.57,
        "lastName": "O'Donnell",
        "votes": 530,
        "total_days": null,
        "total_votes": null,
        "constituency": "Limerick East",
        "member_id": "Kieran-O'Donnell.D.2007-06-14",
        "fullName": "Kieran O'Donnell",
        "firstName": "Kieran",
        "party": "Fine Gael",
        "office": false
    },
    {
        "percentVotes": 34.7,
        "percent_days": 37.14,
        "lastName": "O'Donoghue",
        "votes": 211,
        "total_days": null,
        "total_votes": null,
        "constituency": "Kerry South",
        "member_id": "John-O'Donoghue.D.1987-03-10",
        "fullName": "John O'Donoghue",
        "firstName": "John",
        "party": "Fianna Fáil",
        "office": false
    },
    {
        "percentVotes": 87.83,
        "percent_days": 84.29,
        "lastName": "O'Dowd",
        "votes": 534,
        "total_days": null,
        "total_votes": null,
        "constituency": "Louth",
        "member_id": "Fergus-O'Dowd.S.1997-09-17",
        "fullName": "Fergus O'Dowd",
        "firstName": "Fergus",
        "party": "Fine Gael",
        "office": false
    },
    {
        "percentVotes": 91.61,
        "percent_days": 84.29,
        "lastName": "O'Flynn",
        "votes": 557,
        "total_days": null,
        "total_votes": null,
        "constituency": "Cork North-Central",
        "member_id": "Noel-O'Flynn.D.1997-06-26",
        "fullName": "Noel O'Flynn",
        "firstName": "Noel",
        "party": "Fianna Fáil",
        "office": false
    },
    {
        "percentVotes": 91.94,
        "percent_days": 91.43,
        "lastName": "O'Hanlon",
        "votes": 559,
        "total_days": null,
        "total_votes": null,
        "constituency": "Cavan-Monaghan",
        "member_id": "Rory-O'Hanlon.D.1977-07-05",
        "fullName": "Rory O'Hanlon",
        "firstName": "Rory",
        "party": "Fianna Fáil",
        "office": false
    },
    {
        "percentVotes": 82.73,
        "percent_days": 75.71,
        "lastName": "O'Keeffe",
        "votes": 503,
        "total_days": null,
        "total_votes": null,
        "constituency": "Cork North-West",
        "member_id": "Batt-O'Keeffe.D.1987-03-10",
        "fullName": "Batt O'Keeffe",
        "firstName": "Batt",
        "party": "Fianna Fáil",
        "office": false
    },
    {
        "percentVotes": 78.78,
        "percent_days": 71.43,
        "lastName": "O'Keeffe",
        "votes": 479,
        "total_days": null,
        "total_votes": null,
        "constituency": "Cork South-West",
        "member_id": "Jim-O'Keeffe.D.1977-07-05",
        "fullName": "Jim O'Keeffe",
        "firstName": "Jim",
        "party": "Fine Gael",
        "office": false
    },
    {
        "percentVotes": 78.95,
        "percent_days": 71.43,
        "lastName": "O'Keeffe",
        "votes": 480,
        "total_days": null,
        "total_votes": null,
        "constituency": "Cork East",
        "member_id": "Ned-O'Keeffe.S.1982-05-13",
        "fullName": "Ned O'Keeffe",
        "firstName": "Ned",
        "party": "Fianna Fáil",
        "office": false
    },
    {
        "percentVotes": 85.86,
        "percent_days": 88.57,
        "lastName": "O'Mahony",
        "votes": 522,
        "total_days": null,
        "total_votes": null,
        "constituency": "Mayo",
        "member_id": "John-O'Mahony.D.2007-06-14",
        "fullName": "John O'Mahony",
        "firstName": "John",
        "party": "Fine Gael",
        "office": false
    },
    {
        "percentVotes": 93.91,
        "percent_days": 87.14,
        "lastName": "O'Rourke",
        "votes": 571,
        "total_days": null,
        "total_votes": null,
        "constituency": "Longford-Westmeath",
        "member_id": "Mary-O'Rourke.S.1981-10-08",
        "fullName": "Mary O'Rourke",
        "firstName": "Mary",
        "party": "Fianna Fáil",
        "office": false
    },
    {
        "percentVotes": 88.98,
        "percent_days": 90.0,
        "lastName": "O'Shea",
        "votes": 541,
        "total_days": null,
        "total_votes": null,
        "constituency": "Waterford",
        "member_id": "Brian-O'Shea.S.1987-04-25",
        "fullName": "Brian O'Shea",
        "firstName": "Brian",
        "party": "Labour Party",
        "office": false
    },
    {
        "percentVotes": 92.11,
        "percent_days": 90.0,
        "lastName": "O'Sullivan",
        "votes": 560,
        "total_days": null,
        "total_votes": null,
        "constituency": "Cork South-West",
        "member_id": "Christy-O'Sullivan.D.2007-06-14",
        "fullName": "Christy O'Sullivan",
        "firstName": "Christy",
        "party": "Fianna Fáil",
        "office": false
    },
    {
        "percentVotes": 92.27,
        "percent_days": 90.0,
        "lastName": "O'Sullivan",
        "votes": 561,
        "total_days": null,
        "total_votes": null,
        "constituency": "Limerick East",
        "member_id": "Jan-O'Sullivan.S.1993-02-17",
        "fullName": "Jan O'Sullivan",
        "firstName": "Jan",
        "party": "Labour Party",
        "office": false
    },
    {
        "percentVotes": 80.5,
        "percent_days": 77.78,
        "lastName": "O'Sullivan",
        "votes": 260,
        "total_days": 36,
        "total_votes": 323,
        "constituency": "Dublin Central",
        "member_id": "Maureen-O'Sullivan.D.2009-06-05",
        "fullName": "Maureen O'Sullivan",
        "firstName": "Maureen",
        "party": "Independent",
        "office": false
    },
    {
        "percentVotes": 85.86,
        "percent_days": 75.71,
        "lastName": "Penrose",
        "votes": 522,
        "total_days": null,
        "total_votes": null,
        "constituency": "Longford-Westmeath",
        "member_id": "Willie-Penrose.D.1992-12-14",
        "fullName": "Willie Penrose",
        "firstName": "Willie",
        "party": "Labour Party",
        "office": false
    },
    {
        "percentVotes": 80.43,
        "percent_days": 78.57,
        "lastName": "Perry",
        "votes": 489,
        "total_days": null,
        "total_votes": null,
        "constituency": "Sligo-North Leitrim",
        "member_id": "John-Perry.D.1997-06-26",
        "fullName": "John Perry",
        "firstName": "John",
        "party": "Fine Gael",
        "office": false
    },
    {
        "percentVotes": 73.19,
        "percent_days": 68.57,
        "lastName": "Power",
        "votes": 445,
        "total_days": null,
        "total_votes": null,
        "constituency": "Limerick East",
        "member_id": "Peter-Power.D.2002-06-06",
        "fullName": "Peter Power",
        "firstName": "Peter",
        "party": "Fianna Fáil",
        "office": false
    },
    {
        "percentVotes": 85.2,
        "percent_days": 85.71,
        "lastName": "Power",
        "votes": 518,
        "total_days": null,
        "total_votes": null,
        "constituency": "Kildare South",
        "member_id": "Seán-Power.D.1989-06-29",
        "fullName": "Seán Power",
        "firstName": "Seán",
        "party": "Fianna Fáil",
        "office": false
    },
    {
        "percentVotes": 68.91,
        "percent_days": 74.29,
        "lastName": "Quinn",
        "votes": 419,
        "total_days": null,
        "total_votes": null,
        "constituency": "Dublin South-East",
        "member_id": "Ruairí-Quinn.S.1976-07-01",
        "fullName": "Ruairí Quinn",
        "firstName": "Ruairí",
        "party": "Labour Party",
        "office": false
    },
    {
        "percentVotes": 88.82,
        "percent_days": 72.86,
        "lastName": "Rabbitte",
        "votes": 540,
        "total_days": null,
        "total_votes": null,
        "constituency": "Dublin South-West",
        "member_id": "Pat-Rabbitte.D.1989-06-29",
        "fullName": "Pat Rabbitte",
        "firstName": "Pat",
        "party": "Labour Party",
        "office": false
    },
    {
        "percentVotes": 87.83,
        "percent_days": 88.57,
        "lastName": "Reilly",
        "votes": 534,
        "total_days": null,
        "total_votes": null,
        "constituency": "Dublin North",
        "member_id": "James-Reilly.D.2007-06-14",
        "fullName": "James Reilly",
        "firstName": "James",
        "party": "Fine Gael",
        "office": false
    },
    {
        "percentVotes": 86.51,
        "percent_days": 87.14,
        "lastName": "Ring",
        "votes": 526,
        "total_days": null,
        "total_votes": null,
        "constituency": "Mayo",
        "member_id": "Michael-Ring.D.1994-06-09",
        "fullName": "Michael Ring",
        "firstName": "Michael",
        "party": "Fine Gael",
        "office": false
    },
    {
        "percentVotes": 76.64,
        "percent_days": 62.86,
        "lastName": "Roche",
        "votes": 466,
        "total_days": null,
        "total_votes": null,
        "constituency": "Wicklow",
        "member_id": "Dick-Roche.D.1987-03-10",
        "fullName": "Dick Roche",
        "firstName": "Dick",
        "party": "Fianna Fáil",
        "office": false
    },
    {
        "percentVotes": 88.32,
        "percent_days": 81.43,
        "lastName": "Ryan",
        "votes": 537,
        "total_days": null,
        "total_votes": null,
        "constituency": "Dublin South",
        "member_id": "Eamon-Ryan.D.2002-06-06",
        "fullName": "Eamon Ryan",
        "firstName": "Eamon",
        "party": "Green Party",
        "office": false
    },
    {
        "percentVotes": 89.31,
        "percent_days": 85.71,
        "lastName": "Sargent",
        "votes": 543,
        "total_days": null,
        "total_votes": null,
        "constituency": "Dublin North",
        "member_id": "Trevor-Sargent.D.1992-12-14",
        "fullName": "Trevor Sargent",
        "firstName": "Trevor",
        "party": "Green Party",
        "office": false
    },
    {
        "percentVotes": 93.59,
        "percent_days": 92.86,
        "lastName": "Scanlon",
        "votes": 569,
        "total_days": null,
        "total_votes": null,
        "constituency": "Sligo-North Leitrim",
        "member_id": "Eamon-Scanlon.S.2002-09-12",
        "fullName": "Eamon Scanlon",
        "firstName": "Eamon",
        "party": "Independent",
        "office": false
    },
    {
        "percentVotes": 74.01,
        "percent_days": 60.0,
        "lastName": "Shatter",
        "votes": 450,
        "total_days": null,
        "total_votes": null,
        "constituency": "Dublin South",
        "member_id": "Alan-Shatter.D.1981-06-30",
        "fullName": "Alan Shatter",
        "firstName": "Alan",
        "party": "Fine Gael",
        "office": false
    },
    {
        "percentVotes": 87.83,
        "percent_days": 88.57,
        "lastName": "Sheahan",
        "votes": 534,
        "total_days": null,
        "total_votes": null,
        "constituency": "Kerry South",
        "member_id": "Tom-Sheahan.D.2007-06-14",
        "fullName": "Tom Sheahan",
        "firstName": "Tom",
        "party": "Fine Gael",
        "office": false
    },
    {
        "percentVotes": 84.38,
        "percent_days": 82.86,
        "lastName": "Sheehan",
        "votes": 513,
        "total_days": null,
        "total_votes": null,
        "constituency": "Cork South-West",
        "member_id": "P-J-Sheehan.D.1981-06-30",
        "fullName": "P. J. Sheehan",
        "firstName": "P. J.",
        "party": "Fine Gael",
        "office": false
    },
    {
        "percentVotes": 90.13,
        "percent_days": 81.43,
        "lastName": "Sherlock",
        "votes": 548,
        "total_days": null,
        "total_votes": null,
        "constituency": "Cork East",
        "member_id": "Seán-Sherlock.D.2007-06-14",
        "fullName": "Seán Sherlock",
        "firstName": "Seán",
        "party": "Labour Party",
        "office": false
    },
    {
        "percentVotes": 81.74,
        "percent_days": 72.86,
        "lastName": "Shortall",
        "votes": 497,
        "total_days": null,
        "total_votes": null,
        "constituency": "Dublin North-West",
        "member_id": "Róisín-Shortall.D.1992-12-14",
        "fullName": "Róisín Shortall",
        "firstName": "Róisín",
        "party": "Labour Party",
        "office": false
    },
    {
        "percentVotes": 86.18,
        "percent_days": 87.14,
        "lastName": "Smith",
        "votes": 524,
        "total_days": null,
        "total_votes": null,
        "constituency": "Cavan-Monaghan",
        "member_id": "Brendan-Smith.D.1992-12-14",
        "fullName": "Brendan Smith",
        "firstName": "Brendan",
        "party": "Fianna Fáil",
        "office": false
    },
    {
        "percentVotes": 94.74,
        "percent_days": 92.86,
        "lastName": "Stagg",
        "votes": 576,
        "total_days": null,
        "total_votes": null,
        "constituency": "Kildare North",
        "member_id": "Emmet-Stagg.D.1987-03-10",
        "fullName": "Emmet Stagg",
        "firstName": "Emmet",
        "party": "Labour Party",
        "office": false
    },
    {
        "percentVotes": 88.82,
        "percent_days": 85.71,
        "lastName": "Stanton",
        "votes": 540,
        "total_days": null,
        "total_votes": null,
        "constituency": "Cork East",
        "member_id": "David-Stanton.D.1997-06-26",
        "fullName": "David Stanton",
        "firstName": "David",
        "party": "Fine Gael",
        "office": false
    },
    {
        "percentVotes": 82.57,
        "percent_days": 71.43,
        "lastName": "Timmins",
        "votes": 502,
        "total_days": null,
        "total_votes": null,
        "constituency": "Wicklow",
        "member_id": "Billy-Timmins.D.1997-06-26",
        "fullName": "Billy Timmins",
        "firstName": "Billy",
        "party": "Fine Gael",
        "office": false
    },
    {
        "percentVotes": 88.98,
        "percent_days": 88.57,
        "lastName": "Treacy",
        "votes": 541,
        "total_days": null,
        "total_votes": null,
        "constituency": "Galway East",
        "member_id": "Noel-Treacy.D.1982-07-20",
        "fullName": "Noel Treacy",
        "firstName": "Noel",
        "party": "Fianna Fáil",
        "office": false
    },
    {
        "percentVotes": 91.61,
        "percent_days": 88.57,
        "lastName": "Tuffy",
        "votes": 557,
        "total_days": null,
        "total_votes": null,
        "constituency": "Dublin Mid-West",
        "member_id": "Joanna-Tuffy.S.2002-09-12",
        "fullName": "Joanna Tuffy",
        "firstName": "Joanna",
        "party": "Labour Party",
        "office": false
    },
    {
        "percentVotes": 94.74,
        "percent_days": 94.29,
        "lastName": "Upton",
        "votes": 576,
        "total_days": null,
        "total_votes": null,
        "constituency": "Dublin South-Central",
        "member_id": "Mary-Upton.D.1999-10-27",
        "fullName": "Mary Upton",
        "firstName": "Mary",
        "party": "Labour Party",
        "office": false
    },
    {
        "percentVotes": 70.39,
        "percent_days": 51.43,
        "lastName": "Varadkar",
        "votes": 428,
        "total_days": null,
        "total_votes": null,
        "constituency": "Dublin West",
        "member_id": "Leo-Varadkar.D.2007-06-14",
        "fullName": "Leo Varadkar",
        "firstName": "Leo",
        "party": "Fine Gael",
        "office": false
    },
    {
        "percentVotes": 74.67,
        "percent_days": 61.43,
        "lastName": "Wall",
        "votes": 454,
        "total_days": null,
        "total_votes": null,
        "constituency": "Kildare South",
        "member_id": "Jack-Wall.S.1993-02-17",
        "fullName": "Jack Wall",
        "firstName": "Jack",
        "party": "Labour Party",
        "office": false
    },
    {
        "percentVotes": 92.76,
        "percent_days": 90.0,
        "lastName": "Wallace",
        "votes": 564,
        "total_days": null,
        "total_votes": null,
        "constituency": "Meath East",
        "member_id": "Mary-Wallace.S.1987-04-25",
        "fullName": "Mary Wallace",
        "firstName": "Mary",
        "party": "Fianna Fáil",
        "office": false
    },
    {
        "percentVotes": 98.03,
        "percent_days": 97.14,
        "lastName": "White",
        "votes": 596,
        "total_days": null,
        "total_votes": null,
        "constituency": "Carlow-Kilkenny",
        "member_id": "Mary-White.D.2007-06-14",
        "fullName": "Mary White",
        "firstName": "Mary",
        "party": "Green Party",
        "office": false
    },
    {
        "percentVotes": 90.62,
        "percent_days": 84.29,
        "lastName": "Woods",
        "votes": 551,
        "total_days": null,
        "total_votes": null,
        "constituency": "Dublin North-East",
        "member_id": "Michael-Woods.D.1977-07-05",
        "fullName": "Michael Woods",
        "firstName": "Michael",
        "party": "Fianna Fáil",
        "office": false
    },
    {
        "percentVotes": 87.34,
        "percent_days": 85.71,
        "lastName": "Ó Caoláin",
        "votes": 531,
        "total_days": null,
        "total_votes": null,
        "constituency": "Cavan-Monaghan",
        "member_id": "Caoimhghín-Ó-Caoláin.D.1997-06-26",
        "fullName": "Caoimhghín Ó Caoláin",
        "firstName": "Caoimhghín",
        "party": "Sinn Féin",
        "office": false
    },
    {
        "percentVotes": 90.3,
        "percent_days": 85.71,
        "lastName": "Ó Cuív",
        "votes": 549,
        "total_days": null,
        "total_votes": null,
        "constituency": "Galway West",
        "member_id": "Éamon-Ó-Cuív.S.1989-10-01",
        "fullName": "Éamon Ó Cuív",
        "firstName": "Éamon",
        "party": "Fianna Fáil",
        "office": false
    },
    {
        "percentVotes": 98.36,
        "percent_days": 100.0,
        "lastName": "Ó Fearghaíl",
        "votes": 598,
        "total_days": null,
        "total_votes": null,
        "constituency": "Kildare South",
        "member_id": "Seán-Ó-Fearghaíl.S.2000-06-09",
        "fullName": "Seán Ó Fearghaíl",
        "firstName": "Seán",
        "party": "Fianna Fáil",
        "office": false
    },
    {
        "percentVotes": 86.68,
        "percent_days": 80.0,
        "lastName": "Ó Snodaigh",
        "votes": 527,
        "total_days": null,
        "total_votes": null,
        "constituency": "Dublin South-Central",
        "member_id": "Aengus-Ó-Snodaigh.D.2002-06-06",
        "fullName": "Aengus Ó Snodaigh",
        "firstName": "Aengus",
        "party": "Sinn Féin",
        "office": false
    }
]